llm_llamafile.py
llm_llamafile-0.1.dist-info/LICENSE
llm_llamafile-0.1.dist-info/METADATA
llm_llamafile-0.1.dist-info/WHEEL
llm_llamafile-0.1.dist-info/entry_points.txt
llm_llamafile-0.1.dist-info/top_level.txt
llm_llamafile-0.1.dist-info/RECORD
