Metadata-Version: 2.1
Name: llm-llamafile
Version: 0.1
Summary: Access llamafile localhost models via LLM
Author: Simon Willison
License: Apache-2.0
Project-URL: Homepage, https://github.com/simonw/llm-llamafile
Project-URL: Changelog, https://github.com/simonw/llm-llamafile/releases
Project-URL: Issues, https://github.com/simonw/llm-llamafile/issues
Project-URL: CI, https://github.com/simonw/llm-llamafile/actions
Classifier: License :: OSI Approved :: Apache Software License
License-File: LICENSE
Requires-Dist: llm
Provides-Extra: test
Requires-Dist: pytest ; extra == 'test'
